quokkas/__init__.py
quokkas/__pycache__/__init__.cpython-37.pyc
quokkas/__pycache__/__init__.cpython-38.pyc
quokkas/core/export.py
quokkas/core/__pycache__/dataframe.cpython-38.pyc
quokkas/core/__pycache__/export.cpython-37.pyc
quokkas/core/__pycache__/export.cpython-38.pyc
quokkas/core/__pycache__/ndframe.cpython-38.pyc
quokkas/core/__pycache__/pipeline.cpython-38.pyc
quokkas/core/frames/dataframe.py
quokkas/core/frames/functional.py
quokkas/core/frames/__pycache__/dataframe.cpython-37.pyc
quokkas/core/frames/__pycache__/dataframe.cpython-38.pyc
quokkas/core/frames/__pycache__/functional.cpython-37.pyc
quokkas/core/frames/__pycache__/functional.cpython-38.pyc
quokkas/core/frames/__pycache__/ndframe.cpython-38.pyc
quokkas/core/generic/algos.py
quokkas/core/generic/__pycache__/algos.cpython-37.pyc
quokkas/core/generic/__pycache__/algos.cpython-38.pyc
quokkas/core/pipeline/completion.py
quokkas/core/pipeline/inception.py
quokkas/core/pipeline/lock.py
quokkas/core/pipeline/mode.py
quokkas/core/pipeline/pipeline.py
quokkas/core/pipeline/__pycache__/completion.cpython-37.pyc
quokkas/core/pipeline/__pycache__/completion.cpython-38.pyc
quokkas/core/pipeline/__pycache__/inception.cpython-37.pyc
quokkas/core/pipeline/__pycache__/inception.cpython-38.pyc
quokkas/core/pipeline/__pycache__/lock.cpython-37.pyc
quokkas/core/pipeline/__pycache__/lock.cpython-38.pyc
quokkas/core/pipeline/__pycache__/mode.cpython-37.pyc
quokkas/core/pipeline/__pycache__/mode.cpython-38.pyc
quokkas/core/pipeline/__pycache__/pipeline.cpython-37.pyc
quokkas/core/pipeline/__pycache__/pipeline.cpython-38.pyc
quokkas/eda/categorical.py
quokkas/eda/correlation.py
quokkas/eda/distributions.py
quokkas/eda/export.py
quokkas/eda/feature_importance.py
quokkas/eda/generic.py
quokkas/eda/missing.py
quokkas/eda/scatters.py
quokkas/eda/__pycache__/categorical.cpython-37.pyc
quokkas/eda/__pycache__/categorical.cpython-38.pyc
quokkas/eda/__pycache__/correlation.cpython-37.pyc
quokkas-0.0.4.dist-info/LICENSE
quokkas-0.0.4.dist-info/METADATA
quokkas-0.0.4.dist-info/WHEEL
quokkas-0.0.4.dist-info/top_level.txt
quokkas-0.0.4.dist-info/RECORD
